asgi.py
workers/__init__.py
workers/_workers.py
workers/workflows.py
python_workers_runtime_types1-0.1.0.dist-info/METADATA
python_workers_runtime_types1-0.1.0.dist-info/WHEEL
python_workers_runtime_types1-0.1.0.dist-info/RECORD
